aicomp/__init__.py
aicomp/datasets/__init__.py
aicomp/datasets/base_dataset.py
aicomp/datasets/data_augmentation.py
aicomp/datasets/dataset_factory.py
aicomp/evaluation/__init__.py
aicomp/models/__init__.py
aicomp/models/mtmodel.py
aicomp/models/bert/train_bert.py
aicomp/optimizers/__init__.py
aicomp/schedulers/__init__.py
aicomp/trainers/__init__.py
aicomp/transforms/__init__.py
aicomp/utils/__init__.py
aicomp/utils/base_factory.py
aicomp/utils/load_modules.py
aicomp/utils/utils.py
aicomp-0.1.1.dist-info/METADATA
aicomp-0.1.1.dist-info/WHEEL
aicomp-0.1.1.dist-info/top_level.txt
aicomp-0.1.1.dist-info/RECORD
