Metadata-Version: 2.4
Name: aicomp
Version: 0.1.1
Summary: AI Competition - Multi-task learning for mathematics misconception detection
Author-email: Marco Furrer <your.email@example.com>
License: MIT
Project-URL: Homepage, https://github.com/yourusername/aicomp
Project-URL: Repository, https://github.com/yourusername/aicomp.git
Keywords: transformers,machine-learning,multi-task-learning
Classifier: Development Status :: 3 - Alpha
Classifier: Intended Audience :: Developers
Classifier: License :: OSI Approved :: MIT License
Classifier: Programming Language :: Python :: 3.12
Requires-Python: >=3.11
Requires-Dist: transformers[torch]
Requires-Dist: scikit-learn
Requires-Dist: pandas
Requires-Dist: numpy
Requires-Dist: tqdm
Requires-Dist: accelerate
Requires-Dist: peft
Requires-Dist: python-dotenv
Requires-Dist: huggingface_hub
Requires-Dist: langchain
Requires-Dist: datasets
Requires-Dist: matplotlib
Requires-Dist: bitsandbytes
Requires-Dist: ipywidgets
Requires-Dist: twine
